LICENSE.md
MANIFEST.in
README.rst
setup.py
test.py
boolean/__init__.py
boolean.egg-info/PKG-INFO
boolean.egg-info/SOURCES.txt
boolean.egg-info/dependency_links.txt
boolean.egg-info/not-zip-safe
boolean.egg-info/top_level.txt