Metadata-Version: 1.0
Name: boolean
Version: 1.1.0
Summary: Converts string to their equivalent boolean value
Home-page: https://github.com/scisco/boolean
Author: Alireza J (Scisco)
Author-email: scisco7@gmail.com
License: CC0
Keywords: boolean true false yes no
Platform: UNKNOWN
